rajesh_check_this_out/__init__.py
rajesh_check_this_out/display.py
rajesh_check_this_out-0.1.0.dist-info/METADATA
rajesh_check_this_out-0.1.0.dist-info/WHEEL
rajesh_check_this_out-0.1.0.dist-info/top_level.txt
rajesh_check_this_out-0.1.0.dist-info/RECORD
